[
  "Input:\n|  | 2007 | 2006 | 2005 | 2004 | 2003 |\n|---|---|---|---|---|---|\n| Revenues | $ 636,406 | $ 428,672 | $283,115 | $ 210,015 | $ 161,259 |\n| Total costs and operating expenses | 491,478 | 345,566 | 209,740 | 161,048 | 172,370 |\n| Operating income (loss) | 144,928 | 83,106 | 73,375 | 48,967 | (11,111) |\n| Net income (loss) | 100,967 | 57,401 | 327,998 | 34,364 | (29,281) |\n| Net income (loss) per weighted average share: |  |  |  |  |  |\n| Basic | $ 0.62 | $ 0.37 | $ 2.41 | $ 0.28 | $ (0.25) |\n| Diluted | $ 0.56 | $ 0.34 | $ 2.11 | $ 0.25 | $ (0.25) |\n| Weighted average shares used in per share calculation: |  |  |  |  |  |\n| Basic | 162,959 | 155,366 | 136,167 | 124,407 | 118,075 |\n| Diluted | 185,094 | 176,767 | 156,944 | 146,595 | 118,075 |\n|  |  |  |  |  |  |\n|  |  |  |  |  |  |\n|  |  |  |  |  |  |\n|  | 2007 | 2006 | 2005 | 2004 | 2003 |\n| Cash, cash equivalents and marketable securities | $ 629,895 | $ 430,247 | $309,574 | $ 103,763 | $ 198,707 |\n| Restricted cash | \u2014 | \u2014 | \u2014 | \u2014 | 5,000 |\n| Restricted marketable securities | 3,613 | 4,207 | 4,555 | 4,654 | 4,648 |\n| Working capital | 606,667 | 285,409 | 293,122 | 61,903 | 139,756 |\n| Total assets | 1,656,047 | 1,247,932 | 891,499 | 182,743 | 278,941 |\n| Current portion of 5\u00bd% convertible subordinated notes | \u2014 | \u2014 | \u2014 | \u2014 | 15,000 |\n| Other long-term liabilities | 9,265 | 3,657 | 3,565 | 3,035 | 1,994 |\n| 1% convertible senior notes | 199,855 | 200,000 | 200,000 | 200,000 | 175,000 |\n| 5\u00bd% convertible subordinated notes, net of current portion | \u2014 | \u2014 | \u2014 | 56,614 | 211,000 |\n| Total stockholders\u2019 equity (deficit) | $1,358,552 | $ 954,693 | $624,214 | $(125,931) | $(175,354) |\n\nOutput:\n[\n    {\"row\": \"Revenues\", \"column\": \"2007\", \"value\": \"636,406\", \"units\": \"thousand\"},\n    {\"row\": \"Revenues\", \"column\": \"2006\", \"value\": \"428,672\", \"units\": \"thousand\"},\n    {\"row\": \"Revenues\", \"column\": \"2005\", \"value\": \"283,115\", \"units\": \"thousand\"},\n    {\"row\": \"Revenues\", \"column\": \"2004\", \"value\": \"210,015\", \"units\": \"thousand\"},\n    {\"row\": \"Revenues\", \"column\": \"2003\", \"value\": \"161,259\", \"units\": \"thousand\"},\n    {\"row\": \"Total costs and operating expenses\", \"column\": \"2007\", \"value\": \"491,478\", \"units\": \"thousand\"},\n    {\"row\": \"Total costs and operating expenses\", \"column\": \"2006\", \"value\": \"345,566\", \"units\": \"thousand\"},\n    {\"row\": \"Total costs and operating expenses\", \"column\": \"2005\", \"value\": \"209,740\", \"units\": \"thousand\"},\n    {\"row\": \"Total costs and operating expenses\", \"column\": \"2004\", \"value\": \"161,048\", \"units\": \"thousand\"},\n    {\"row\": \"Total costs and operating expenses\", \"column\": \"2003\", \"value\": \"172,370\", \"units\": \"thousand\"},\n    {\"row\": \"Operating income (loss)\", \"column\": \"2007\", \"value\": \"144,928\", \"units\": \"thousand\"},\n    {\"row\": \"Operating income (loss)\", \"column\": \"2006\", \"value\": \"83,106\", \"units\": \"thousand\"},\n    {\"row\": \"Operating income (loss)\", \"column\": \"2005\", \"value\": \"73,375\", \"units\": \"thousand\"},\n    {\"row\": \"Operating income (loss)\", \"column\": \"2004\", \"value\": \"48,967\", \"units\": \"thousand\"},\n    {\"row\": \"Operating income (loss)\", \"column\": \"2003\", \"value\": \"(11,111)\", \"units\": \"thousand\"},\n    {\"row\": \"Net income (loss)\", \"column\": \"2007\", \"value\": \"100,967\", \"units\": \"thousand\"},\n    {\"row\": \"Net income (loss)\", \"column\": \"2006\", \"value\": \"57,401\", \"units\": \"thousand\"},\n    {\"row\": \"Net income (loss)\", \"column\": \"2005\", \"value\": \"327,998\", \"units\": \"thousand\"},\n    {\"row\": \"Net income (loss)\", \"column\": \"2004\", \"value\": \"34,364\", \"units\": \"thousand\"},\n    {\"row\": \"Net income (loss)\", \"column\": \"2003\", \"value\": \"(29,281)\", \"units\": \"thousand\"},\n    {\"row\": \"Net income (loss) per weighted average share:\", \"column\": \"Basic\", \"value\": \"$ 0.62\", \"units\": \"null\"},\n    {\"row\": \"Net income (loss) per weighted average share:\", \"column\": \"2007\", \"value\": \"$ 0.62\", \"units\": \"null\"},\n    {\"row\": \"Net income (loss) per weighted average share:\", \"column\": \"2006\", \"value\": \"$ 0.37\", \"units\": \"null\"},\n    {\"row\": \"Net income (loss) per weighted average share:\", \"column\": \"2005\", \"value\": \"$ 2.41\", \"units\": \"null\"},\n    {\"row\": \"Net income (loss) per weighted average share:\", \"column\": \"2004\", \"value\": \"$ 0.28\", \"units\": \"null\"},\n    {\"row\": \"Net income (loss) per weighted average share:\", \"column\": \"2003\", \"value\": \"$ (0.25)\", \"units\": \"null\"},\n    {\"row\": \"Net income (loss) per weighted average share:\", \"column\": \"Diluted\", \"value\": \"$ 0.56\", \"units\": \"null\"},\n    {\"row\": \"Net income (loss) per weighted average share:\", \"column\": \"2007\", \"value\": \"$ 0.56\", \"units\": \"null\"},\n    {\"row\": \"Net income (loss) per weighted average share:\", \"column\": \"2006\", \"value\": \"$ 0.34\", \"units\": \"null\"},\n    {\"row\": \"Net income (loss) per weighted average share:\", \"column\": \"2005\", \"value\": \"$ 2.11\", \"units\": \"null\"},\n    {\"row\": \"Net income (loss) per weighted average share:\", \"column\": \"2004\", \"value\": \"$ 0.25\", \"units\": \"null\"},\n    {\"row\": \"Net income (loss) per weighted average share:\", \"column\": \"2003\", \"value\": \"$ (0.25)\", \"units\": \"null\"},\n    {\"row\": \"Weighted average shares used in per share calculation:\", \"column\": \"Basic\", \"value\": \"162,959\", \"units\": \"null\"},\n    {\"row\": \"Weighted average shares used in per share calculation:\", \"column\": \"2007\", \"value\": \"162,959\", \"units\": \"null\"},\n    {\"row\": \"Weighted average shares used in per share calculation:\", \"column\": \"2006\", \"value\": \"155,366\", \"units\": \"null\"},\n    {\"row\": \"Weighted average shares used in per share calculation:\", \"column\": \"2005\", \"value\": \"136,167\", \"units\": \"null\"},\n    {\"row\": \"Weighted average shares used in per share calculation:\", \"column\": \"2004\", \"value\": \"124,407\", \"units\": \"null\"},\n    {\"row\": \"Weighted average shares used in per share calculation:\", \"column\": \"2003\", \"value\": \"118,075\", \"units\": \"null\"},\n    {\"row\": \"Weighted average shares used in per share calculation:\", \"column\": \"Diluted\", \"value\": \"185,094\", \"units\": \"null\"},\n    {\"row\": \"Weighted average shares used in per share calculation:\", \"column\": \"2007\", \"value\": \"185,094\", \"units\": \"null\"},\n    {\"row\": \"Weighted average shares used in per share calculation:\", \"column\": \"2006\", \"value\": \"176,767\", \"units\": \"null\"},\n    {\"row\": \"Weighted average shares used in per share calculation:\", \"column\": \"2005\", \"value\": \"156,944\", \"units\": \"null\"},\n    {\"row\": \"Weighted average shares used in per share calculation:\", \"column\": \"2004\", \"value\": \"146,595\", \"units\": \"null\"},\n    {\"row\": \"Weighted average shares used in per share calculation:\", \"column\": \"2003\", \"value\": \"118,075\", \"units\": \"null\"},\n    {\"row\": \"Cash, cash equivalents and marketable securities\", \"column\": \"2007\", \"value\": \"629,895\", \"units\": \"thousand\"},\n    {\"row\": \"Cash, cash equivalents and marketable securities\", \"column\": \"2006\", \"value\": \"430,247\", \"units\": \"thousand\"},\n    {\"row\": \"Cash, cash equivalents and marketable securities\", \"column\": \"2005\", \"value\": \"309,574\", \"units\": \"thousand\"},\n    {\"row\": \"Cash, cash equivalents and marketable securities\", \"column\": \"2004\", \"value\": \"103,763\", \"units\": \"thousand\"},\n    {\"row\": \"Cash, cash equivalents and marketable securities\", \"column\": \"2003\", \"value\": \"198,707\", \"units\": \"thousand\"},\n    {\"row\": \"Restricted cash\", \"column\": \"2007\", \"value\": \"3,613\", \"units\": \"thousand\"},\n    {\"row\": \"Restricted cash\", \"column\": \"2006\", \"value\": \"4,207\", \"units\": \"thousand\"},\n    {\"row\": \"Restricted cash\", \"column\": \"2005\", \"value\": \"4,555\", \"units\": \"thousand\"},\n    {\"row\": \"Restricted cash\", \"column\": \"2004\", \"value\": \"4,654\", \"units\": \"thousand\"},\n    {\"row\": \"Restricted cash\", \"column\": \"2003\", \"value\": \"4,648\", \"units\": \"thousand\"},\n    {\"row\": \"Restricted marketable securities\", \"column\": \"2007\", \"value\": \"\u2014\", \"units\": \"null\"},\n    {\"row\": \"Restricted marketable securities\", \"column\": \"2006\", \"value\": \"\u2014\", \"units\": \"null\"},\n    {\"row\": \"Restricted marketable securities\", \"column\": \"2005\", \"value\": \"\u2014\", \"units\": \"null\"},\n    {\"row\": \"Restricted marketable securities\", \"column\": \"2004\", \"value\": \"\u2014\", \"units\": \"null\"},\n    {\"row\": \"Restricted marketable securities\", \"column\": \"2003\", \"value\": \"5,000\", \"units\": \"thousand\"},\n    {\"row\": \"Working capital\", \"column\": \"2007\", \"value\": \"606,667\", \"units\": \"thousand\"},\n    {\"row\": \"Working capital\", \"column\": \"2006\", \"value\": \"285,409\", \"units\": \"thousand\"},\n    {\"row\": \"Working capital\", \"column\": \"2005\", \"value\": \"293,122\", \"units\": \"thousand\"},\n    {\"row\": \"Working capital\", \"column\": \"2004\", \"value\": \"61,903\", \"units\": \"thousand\"},\n    {\"row\": \"Working capital\", \"column\": \"2003\", \"value\": \"139,756\", \"units\": \"thousand\"},\n    {\"row\": \"Total assets\", \"column\": \"2007\", \"value\": \"1,656,047\", \"units\": \"thousand\"},\n    {\"row\": \"Total assets\", \"column\": \"2006\", \"value\": \"1,247,932\", \"units\": \"thousand\"},\n    {\"row\": \"Total assets\", \"column\": \"2005\", \"value\": \"891,499\", \"units\": \"thousand\"},\n    {\"row\": \"Total assets\", \"column\": \"2004\", \"value\": \"182,743\", \"units\": \"thousand\"},\n    {\"row\": \"Total assets\", \"column\": \"2003\", \"value\": \"278,941\", \"units\": \"thousand\"},\n    {\"row\": \"Current portion of 5\u00bd% convertible subordinated notes\", \"column\": \"2007\", \"value\": \"\u2014\", \"units\": \"null\"},\n    {\"row\": \"Current portion of 5\u00bd% convertible subordinated notes\", \"column\": \"2006\", \"value\": \"\u2014\", \"units\": \"null\"},\n    {\"row\": \"Current portion of 5\u00bd% convertible subordinated notes\", \"column\": \"2005\", \"value\": \"\u2014\", \"units\": \"null\"},\n    {\"row\": \"Current portion of 5\u00bd% convertible subordinated notes\", \"column\": \"2004\", \"value\": \"\u2014\", \"units\": \"null\"},\n    {\"row\": \"Current portion of 5\u00bd% convertible subordinated notes\", \"column\": \"2003\", \"value\": \"15,000\", \"units\": \"thousand\"},\n    {\"row\": \"Other long-term liabilities\", \"column\": \"2007\", \"value\": \"9,265\", \"units\": \"thousand\"},\n    {\"row\": \"Other long-term liabilities\", \"column\": \"2006\", \"value\": \"3,657\", \"units\": \"thousand\"},\n    {\"row\": \"Other long-term liabilities\", \"column\": \"2005\", \"value\": \"3,565\", \"units\": \"thousand\"},\n    {\"row\": \"Other long-term liabilities\", \"column\": \"2004\", \"value\": \"3,035\", \"units\": \"thousand\"},\n    {\"row\": \"Other long-term liabilities\", \"column\": \"2003\", \"value\": \"1,994\", \"units\": \"thousand\"},\n    {\"row\": \"1% convertible senior notes\", \"column\": \"2007\", \"value\": \"199,855\", \"units\": \"thousand\"},\n    {\"row\": \"1% convertible senior notes\", \"column\": \"2006\", \"value\": \"200,000\", \"units\": \"thousand\"},\n    {\"row\": \"1% convertible senior notes\", \"column\": \"2005\", \"value\": \"200,000\", \"units\": \"thousand\"},\n    {\"row\": \"1% convertible senior notes\", \"column\": \"2004\", \"value\": \"200,000\", \"units\": \"thousand\"},\n    {\"row\": \"1% convertible senior notes\", \"column\": \"2003\", \"value\": \"175,000\", \"units\": \"thousand\"},\n    {\"row\": \"5\u00bd% convertible subordinated notes, net of current portion\", \"column\": \"2007\", \"value\": \"\u2014\", \"units\": \"null\"},\n    {\"row\": \"5\u00bd% convertible subordinated notes, net of current portion\", \"column\": \"2006\", \"value\": \"\u2014\", \"units\": \"null\"},\n    {\"row\": \"5\u00bd% convertible subordinated notes, net of current portion\", \"column\": \"2005\", \"value\": \"\u2014\", \"units\": \"null\"},\n    {\"row\": \"5\u00bd% convertible subordinated notes, net of current portion\", \"column\": \"2004\", \"value\": \"56,614\", \"units\": \"thousand\"},\n    {\"row\": \"5\u00bd% convertible subordinated notes, net of current portion\", \"column\": \"2003\", \"value\": \"211,000\", \"units\": \"thousand\"},\n    {\"row\": \"Total stockholders\u2019 equity (deficit)\", \"column\": \"2007\", \"value\": \"1,358,552\", \"units\": \"thousand\"},\n    {\"row\": \"Total stockholders\u2019 equity (deficit)\", \"column\": \"2006\", \"value\": \"954,693\", \"units\": \"thousand\"},\n    {\"row\": \"Total stockholders\u2019 equity (deficit)\", \"column\": \"2005\", \"value\": \"624,214\", \"units\": \"thousand\"},\n    {\"row\": \"Total stockholders\u2019 equity (deficit)\", \"column\": \"2004\", \"value\": \"(125,931)\", \"units\": \"thousand\"},\n    {\"row\": \"Total stockholders\u2019 equity (deficit)\", \"column\": \"2003\", \"value\": \"(175,354)\", \"units\": \"thousand\"}\n]",
  "Input:\n| Operating Results | 2016^(1) | 2015^(1) | 2014^(1) | 2013^(1) | 2012^(1) |\n|---|---|---|---|---|---|\n| Net Sales | $3,493.1 | 3,394.8 | 3,297.6 | 3,194.3 | 2,921.9 |\n| Marketing expenses | $427.2 | 417.5 | 416.9 | 399.8 | 357.3 |\n| Research and development expenses | $63.2 | 64.7 | 59.8 | 61.8 | 54.8 |\n| Income from Operations^(2,3) | $724.2 | 674.2 | 641.2 | 622.2 | 545.1 |\n| % of Sales | 20.7% | 19.9% | 19.4% | 19.5% | 18.7% |\n| Net Income^(2,4) | $459.0 | 410.4 | 413.9 | 394.4 | 349.8 |\n| Net Income per Share-Basic^(3,4,5) | $1.78 | 1.57 | 1.53 | 1.43 | 1.25 |\n| Net Income per Share-Diluted^(3,4,5) | $1.75 | 1.54 | 1.51 | 1.40 | 1.23 |\n| Financial Position |  |  |  |  |  |\n| Total Assets | $4,354.1 | 4,256.9 | 4,359.2 | 4,237.3 | 4,072.5 |\n| Total Debt^(2) | $1,120.2 | 1,050.0 | 1,086.6 | 797.3 | 895.6 |\n| Total Stockholders\u2019 Equity | $1,977.9 | 2,023.2 | 2,101.9 | 2,300.0 | 2,061.1 |\n| Total Debt as a % of Total Capitalization | 36% | 34% | 34% | 26% | 30% |\n| Other Data |  |  |  |  |  |\n| Average Common Shares Outstanding-Basic^(5) | 257.6 | 262.2 | 270.2 | 277.2 | 280.2 |\n| Cash Dividends Paid | $183.0 | 175.3 | 167.5 | 155.2 | 134.5 |\n| Cash Dividends Paid per Common Share^(5) | $0.71 | 0.67 | 0.62 | 0.56 | 0.48 |\n| Stockholders\u2019 Equity per Common Share^(5) | $7.68 | 7.72 | 7.78 | 8.30 | 7.36 |\n| Additions to Property, Plant & Equipment^(6) | $49.8 | 61.8 | 70.5 | 67.1 | 74.5 |\n| Depreciation & Amortization | $107.6 | 101.0 | 91.2 | 90.5 | 85.0 |\n| Employees at Year-End | 4,500 | 4,406 | 4,145 | 4,177 | 4,354 |\n\nOutput:\n[\n    {\"row\": \"Net Sales\", \"column\": \"2016(1)\", \"value\": \"$3,493.1\", \"units\": \"null\"},\n    {\"row\": \"Net Sales\", \"column\": \"2015(1)\", \"value\": \"3,394.8\", \"units\": \"null\"},\n    {\"row\": \"Net Sales\", \"column\": \"2014(1)\", \"value\": \"3,297.6\", \"units\": \"null\"},\n    {\"row\": \"Net Sales\", \"column\": \"2013(1)\", \"value\": \"3,194.3\", \"units\": \"null\"},\n    {\"row\": \"Net Sales\", \"column\": \"2012(1)\", \"value\": \"2,921.9\", \"units\": \"null\"},\n    {\"row\": \"Marketing expenses\", \"column\": \"2016(1)\", \"value\": \"$ 427.2\", \"units\": \"null\"},\n    {\"row\": \"Marketing expenses\", \"column\": \"2015(1)\", \"value\": \"417.5\", \"units\": \"null\"},\n    {\"row\": \"Marketing expenses\", \"column\": \"2014(1)\", \"value\": \"416.9\", \"units\": \"null\"},\n    {\"row\": \"Marketing expenses\", \"column\": \"2013(1)\", \"value\": \"399.8\", \"units\": \"null\"},\n    {\"row\": \"Marketing expenses\", \"column\": \"2012(1)\", \"value\": \"357.3\", \"units\": \"null\"},\n    {\"row\": \"Research and development expenses\", \"column\": \"2016(1)\", \"value\": \"$ 63.2\", \"units\": \"null\"},\n    {\"row\": \"Research and development expenses\", \"column\": \"2015(1)\", \"value\": \"64.7\", \"units\": \"null\"},\n    {\"row\": \"Research and development expenses\", \"column\": \"2014(1)\", \"value\": \"59.8\", \"units\": \"null\"},\n    {\"row\": \"Research and development expenses\", \"column\": \"2013(1)\", \"value\": \"61.8\", \"units\": \"null\"},\n    {\"row\": \"Research and development expenses\", \"column\": \"2012(1)\", \"value\": \"54.8\", \"units\": \"null\"},\n    {\"row\": \"Income from Operations(2,3)\", \"column\": \"2016(1)\", \"value\": \"$ 724.2\", \"units\": \"null\"},\n    {\"row\": \"Income from Operations(2,3)\", \"column\": \"2015(1)\", \"value\": \"674.2\", \"units\": \"null\"},\n    {\"row\": \"Income from Operations(2,3)\", \"column\": \"2014(1)\", \"value\": \"641.2\", \"units\": \"null\"},\n    {\"row\": \"Income from Operations(2,3)\", \"column\": \"2013(1)\", \"value\": \"622.2\", \"units\": \"null\"},\n    {\"row\": \"Income from Operations(2,3)\", \"column\": \"2012(1)\", \"value\": \"545.1\", \"units\": \"null\"},\n    {\"row\": \"% of Sales\", \"column\": \"2016(1)\", \"value\": \"20.7%\", \"units\": \"null\"},\n    {\"row\": \"% of Sales\", \"column\": \"2015(1)\", \"value\": \"19.9%\", \"units\": \"null\"},\n    {\"row\": \"% of Sales\", \"column\": \"2014(1)\", \"value\": \"19.4%\", \"units\": \"null\"},\n    {\"row\": \"% of Sales\", \"column\": \"2013(1)\", \"value\": \"19.5%\", \"units\": \"null\"},\n    {\"row\": \"% of Sales\", \"column\": \"2012(1)\", \"value\": \"18.7%\", \"units\": \"null\"},\n    {\"row\": \"Net Income(2,4)\", \"column\": \"2016(1)\", \"value\": \"$ 459.0\", \"units\": \"null\"},\n    {\"row\": \"Net Income(2,4)\", \"column\": \"2015(1)\", \"value\": \"410.4\", \"units\": \"null\"},\n    {\"row\": \"Net Income(2,4)\", \"column\": \"2014(1)\", \"value\": \"413.9\", \"units\": \"null\"},\n    {\"row\": \"Net Income(2,4)\", \"column\": \"2013(1)\", \"value\": \"394.4\", \"units\": \"null\"},\n    {\"row\": \"Net Income(2,4)\", \"column\": \"2012(1)\", \"value\": \"349.8\", \"units\": \"null\"},\n    {\"row\": \"Net Income per Share-Basic(3,4,5)\", \"column\": \"2016(1)\", \"value\": \"$ 1.78\", \"units\": \"null\"},\n    {\"row\": \"Net Income per Share-Basic(3,4,5)\", \"column\": \"2015(1)\", \"value\": \"1.57\", \"units\": \"null\"},\n    {\"row\": \"Net Income per Share-Basic(3,4,5)\", \"column\": \"2014(1)\", \"value\": \"1.53\", \"units\": \"null\"},\n    {\"row\": \"Net Income per Share-Basic(3,4,5)\", \"column\": \"2013(1)\", \"value\": \"1.43\", \"units\": \"null\"},\n    {\"row\": \"Net Income per Share-Basic(3,4,5)\", \"column\": \"2012(1)\", \"value\": \"1.25\", \"units\": \"null\"},\n    {\"row\": \"Net Income per Share-Diluted(3,4,5)\", \"column\": \"2016(1)\", \"value\": \"$ 1.75\", \"units\": \"null\"},\n    {\"row\": \"Net Income per Share-Diluted(3,4,5)\", \"column\": \"2015(1)\", \"value\": \"1.54\", \"units\": \"null\"},\n    {\"row\": \"Net Income per Share-Diluted(3,4,5)\", \"column\": \"2014(1)\", \"value\": \"1.51\", \"units\": \"null\"},\n    {\"row\": \"Net Income per Share-Diluted(3,4,5)\", \"column\": \"2013(1)\", \"value\": \"1.40\", \"units\": \"null\"},\n    {\"row\": \"Net Income per Share-Diluted(3,4,5)\", \"column\": \"2012(1)\", \"value\": \"1.23\", \"units\": \"null\"},\n    {\"row\": \"Total Assets\", \"column\": \"2016(1)\", \"value\": \"$4,354.1\", \"units\": \"null\"},\n    {\"row\": \"Total Assets\", \"column\": \"2015(1)\", \"value\": \"4,256.9\", \"units\": \"null\"},\n    {\"row\": \"Total Assets\", \"column\": \"2014(1)\", \"value\": \"4,359.2\", \"units\": \"null\"},\n    {\"row\": \"Total Assets\", \"column\": \"2013(1)\", \"value\": \"4,237.3\", \"units\": \"null\"},\n    {\"row\": \"Total Assets\", \"column\": \"2012(1)\", \"value\": \"4,072.5\", \"units\": \"null\"},\n    {\"row\": \"Total Debt(2)\", \"column\": \"2016(1)\", \"value\": \"$1,120.2\", \"units\": \"null\"},\n    {\"row\": \"Total Debt(2)\", \"column\": \"2015(1)\", \"value\": \"1,050.0\", \"units\": \"null\"},\n    {\"row\": \"Total Debt(2)\", \"column\": \"2014(1)\", \"value\": \"1,086.6\", \"units\": \"null\"},\n    {\"row\": \"Total Debt(2)\", \"column\": \"2013(1)\", \"value\": \"797.3\", \"units\": \"null\"},\n    {\"row\": \"Total Debt(2)\", \"column\": \"2012(1)\", \"value\": \"895.6\", \"units\": \"null\"},\n    {\"row\": \"Total Stockholders\u2019 Equity\", \"column\": \"2016(1)\", \"value\": \"$1,977.9\", \"units\": \"null\"},\n    {\"row\": \"Total Stockholders\u2019 Equity\", \"column\": \"2015(1)\", \"value\": \"2,023.2\", \"units\": \"null\"},\n    {\"row\": \"Total Stockholders\u2019 Equity\", \"column\": \"2014(1)\", \"value\": \"2,101.9\", \"units\": \"null\"},\n    {\"row\": \"Total Stockholders\u2019 Equity\", \"column\": \"2013(1)\", \"value\": \"2,300.0\", \"units\": \"null\"},\n    {\"row\": \"Total Stockholders\u2019 Equity\", \"column\": \"2012(1)\", \"value\": \"2,061.1\", \"units\": \"null\"},\n    {\"row\": \"Total Debt as % of Total Capitalization\", \"column\": \"2016(1)\", \"value\": \"36%\", \"units\": \"null\"},\n    {\"row\": \"Total Debt as % of Total Capitalization\", \"column\": \"2015(1)\", \"value\": \"34%\", \"units\": \"null\"},\n    {\"row\": \"Total Debt as % of Total Capitalization\", \"column\": \"2014(1)\", \"value\": \"34%\", \"units\": \"null\"},\n    {\"row\": \"Total Debt as % of Total Capitalization\", \"column\": \"2013(1)\", \"value\": \"26%\", \"units\": \"null\"},\n    {\"row\": \"Total Debt as % of Total Capitalization\", \"column\": \"2012(1)\", \"value\": \"30%\", \"units\": \"null\"},\n    {\"row\": \"Average Common Shares Outstanding-Basic(5)\", \"column\": \"2016(1)\", \"value\": \"257.6\", \"units\": \"null\"},\n    {\"row\": \"Average Common Shares Outstanding-Basic(5)\", \"column\": \"2015(1)\", \"value\": \"262.2\", \"units\": \"null\"},\n    {\"row\": \"Average Common Shares Outstanding-Basic(5)\", \"column\": \"2014(1)\", \"value\": \"270.2\", \"units\": \"null\"},\n    {\"row\": \"Average Common Shares Outstanding-Basic(5)\", \"column\": \"2013(1)\", \"value\": \"277.2\", \"units\": \"null\"},\n    {\"row\": \"Average Common Shares Outstanding-Basic(5)\", \"column\": \"2012(1)\", \"value\": \"280.2\", \"units\": \"null\"},\n    {\"row\": \"Cash Dividends Paid\", \"column\": \"2016(1)\", \"value\": \"$ 183.0\", \"units\": \"null\"},\n    {\"row\": \"Cash Dividends Paid\", \"column\": \"2015(1)\", \"value\": \"175.3\", \"units\": \"null\"},\n    {\"row\": \"Cash Dividends Paid\", \"column\": \"2014(1)\", \"value\": \"167.5\", \"units\": \"null\"},\n    {\"row\": \"Cash Dividends Paid\", \"column\": \"2013(1)\", \"value\": \"155.2\", \"units\": \"null\"},\n    {\"row\": \"Cash Dividends Paid\", \"column\": \"2012(1)\", \"value\": \"134.5\", \"units\": \"null\"},\n    {\"row\": \"Cash Dividends Paid per Common Share(5)\", \"column\": \"2016(1)\", \"value\": \"$ 0.71\", \"units\": \"null\"},\n    {\"row\": \"Cash Dividends Paid per Common Share(5)\", \"column\": \"2015(1)\", \"value\": \"0.67\", \"units\": \"null\"},\n    {\"row\": \"Cash Dividends Paid per Common Share(5)\", \"column\": \"2014(1)\", \"value\": \"0.62\", \"units\": \"null\"},\n    {\"row\": \"Cash Dividends Paid per Common Share(5)\", \"column\": \"2013(1)\", \"value\": \"0.56\", \"units\": \"null\"},\n    {\"row\": \"Cash Dividends Paid per Common Share(5)\", \"column\": \"2012(1)\", \"value\": \"0.48\", \"units\": \"null\"},\n    {\"row\": \"Stockholders\u2019 Equity per Common Share(5)\", \"column\": \"2016(1)\", \"value\": \"$ 7.68\", \"units\": \"null\"},\n    {\"row\": \"Stockholders\u2019 Equity per Common Share(5)\", \"column\": \"2015(1)\", \"value\": \"7.72\", \"units\": \"null\"},\n    {\"row\": \"Stockholders\u2019 Equity per Common Share(5)\", \"column\": \"2014(1)\", \"value\": \"7.78\", \"units\": \"null\"},\n    {\"row\": \"Stockholders\u2019 Equity per Common Share(5)\", \"column\": \"2013(1)\", \"value\": \"8.30\", \"units\": \"null\"},\n    {\"row\": \"Stockholders\u2019 Equity per Common Share(5)\", \"column\": \"2012(1)\", \"value\": \"7.36\", \"units\": \"null\"},\n    {\"row\": \"Additions to Property, Plant & Equipment(6)\", \"column\": \"2016(1)\", \"value\": \"$ 49.8\", \"units\": \"null\"},\n    {\"row\": \"Additions to Property, Plant & Equipment(6)\", \"column\": \"2015(1)\", \"value\": \"61.8\", \"units\": \"null\"},\n    {\"row\": \"Additions to Property, Plant & Equipment(6)\", \"column\": \"2014(1)\", \"value\": \"70.5\", \"units\": \"null\"},\n    {\"row\": \"Additions to Property, Plant & Equipment(6)\", \"column\": \"2013(1)\", \"value\": \"67.1\", \"units\": \"null\"},\n    {\"row\": \"Additions to Property, Plant & Equipment(6)\", \"column\": \"2012(1)\", \"value\": \"74.5\", \"units\": \"null\"},\n    {\"row\": \"Depreciation & Amortization\", \"column\": \"2016(1)\", \"value\": \"$ 107.6\", \"units\": \"null\"},\n    {\"row\": \"Depreciation & Amortization\", \"column\": \"2015(1)\", \"value\": \"101.0\", \"units\": \"null\"},\n    {\"row\": \"Depreciation & Amortization\", \"column\": \"2014(1)\", \"value\": \"91.2\", \"units\": \"null\"},\n    {\"row\": \"Depreciation & Amortization\", \"column\": \"2013(1)\", \"value\": \"90.5\", \"units\": \"null\"},\n    {\"row\": \"Depreciation & Amortization\", \"column\": \"2012(1)\", \"value\": \"85.0\", \"units\": \"null\"},\n    {\"row\": \"Employees at Year-End\", \"column\": \"2016(1)\", \"value\": \"4,500\", \"units\": \"null\"},\n    {\"row\": \"Employees at Year-End\", \"column\": \"2015(1)\", \"value\": \"4,406\", \"units\": \"null\"},\n    {\"row\": \"Employees at Year-End\", \"column\": \"2014(1)\", \"value\": \"4,145\", \"units\": \"null\"},\n    {\"row\": \"Employees at Year-End\", \"column\": \"2013(1)\", \"value\": \"4,177\", \"units\": \"null\"},\n    {\"row\": \"Employees at Year-End\", \"column\": \"2012(1)\", \"value\": \"4,354\", \"units\": \"null\"}\n]",
  "Input:\n| Category              | Owned | Leased | Total | Capacity(1) per week at October 3, 2009 | Fiscal 2009 Average Capacity Utilization |\n|-----------------------|-------|--------|-------|----------------------------------------|------------------------------------------|\n| Chicken Segment:      |       |        |       |                                        |                                          |\n| Processing plants     | 61    | 2      | 63    |                                        |                                          |\n| Rendering plants      | 14    | -      | 14    |                                        |                                          |\n| Blending mills        | 2     | -      | 2     |                                        |                                          |\n| Feed mills            | 42    | -      | 42    |                                        |                                          |\n| Broiler hatcheries    | 62    | 7      | 69    |                                        |                                          |\n| Breeder houses        | 483   | 747    | 1,230 |                                        |                                          |\n| Broiler farm houses   | 864   | 812    | 1,676 |                                        |                                          |\n| Beef Segment Production Facilities | 12 | - | 12 |                                        |                                          |\n| Pork Segment Production Facilities | 9 | - | 9 |                                        |                                          |\n| Prepared Foods Segment Processing Plants | 22 | 1 | 23 |                                        |                                          |\n| Distribution Centers | 10    | 2      | 12    |                                        |                                          |\n| Cold Storage Facilities | 65 | 10 | 75    |                                        |                                          |\n| Chicken Processing Plants |       |        |       | 48 million head                       | 90%                                      |\n| Beef Production Facilities |       |        |       | 170,000 head                          | 82%                                      |\n| Pork Production Facilities |       |        |       | 437,000 head                          | 90%                                      |\n| Prepared Foods Processing Plants |       |        |       | 45 million pounds                     | 82%                                      |\n\nOutput:\n[\n    {\"row\": \"Chicken Segment:\", \"column\": \"Owned\", \"value\": null, \"units\": null},\n    {\"row\": \"Chicken Segment:\", \"column\": \"Leased\", \"value\": null, \"units\": null},\n    {\"row\": \"Chicken Segment:\", \"column\": \"Total\", \"value\": null, \"units\": null},\n    {\"row\": \"Processing plants\", \"column\": \"Owned\", \"value\": \"61\", \"units\": null},\n    {\"row\": \"Processing plants\", \"column\": \"Leased\", \"value\": \"2\", \"units\": null},\n    {\"row\": \"Processing plants\", \"column\": \"Total\", \"value\": \"63\", \"units\": null},\n    {\"row\": \"Rendering plants\", \"column\": \"Owned\", \"value\": \"14\", \"units\": null},\n    {\"row\": \"Rendering plants\", \"column\": \"Leased\", \"value\": \"-\", \"units\": null},\n    {\"row\": \"Rendering plants\", \"column\": \"Total\", \"value\": \"14\", \"units\": null},\n    {\"row\": \"Blending mills\", \"column\": \"Owned\", \"value\": \"2\", \"units\": null},\n    {\"row\": \"Blending mills\", \"column\": \"Leased\", \"value\": \"-\", \"units\": null},\n    {\"row\": \"Blending mills\", \"column\": \"Total\", \"value\": \"2\", \"units\": null},\n    {\"row\": \"Feed mills\", \"column\": \"Owned\", \"value\": \"42\", \"units\": null},\n    {\"row\": \"Feed mills\", \"column\": \"Leased\", \"value\": \"-\", \"units\": null},\n    {\"row\": \"Feed mills\", \"column\": \"Total\", \"value\": \"42\", \"units\": null},\n    {\"row\": \"Broiler hatcheries\", \"column\": \"Owned\", \"value\": \"62\", \"units\": null},\n    {\"row\": \"Broiler hatcheries\", \"column\": \"Leased\", \"value\": \"7\", \"units\": null},\n    {\"row\": \"Broiler hatcheries\", \"column\": \"Total\", \"value\": \"69\", \"units\": null},\n    {\"row\": \"Breeder houses\", \"column\": \"Owned\", \"value\": \"483\", \"units\": null},\n    {\"row\": \"Breeder houses\", \"column\": \"Leased\", \"value\": \"747\", \"units\": null},\n    {\"row\": \"Breeder houses\", \"column\": \"Total\", \"value\": \"1,230\", \"units\": null},\n    {\"row\": \"Broiler farm houses\", \"column\": \"Owned\", \"value\": \"864\", \"units\": null},\n    {\"row\": \"Broiler farm houses\", \"column\": \"Leased\", \"value\": \"812\", \"units\": null},\n    {\"row\": \"Broiler farm houses\", \"column\": \"Total\", \"value\": \"1,676\", \"units\": null},\n    {\"row\": \"Beef Segment Production Facilities\", \"column\": \"Owned\", \"value\": \"12\", \"units\": null},\n    {\"row\": \"Beef Segment Production Facilities\", \"column\": \"Leased\", \"value\": \"-\", \"units\": null},\n    {\"row\": \"Beef Segment Production Facilities\", \"column\": \"Total\", \"value\": \"12\", \"units\": null},\n    {\"row\": \"Pork Segment Production Facilities\", \"column\": \"Owned\", \"value\": \"9\", \"units\": null},\n    {\"row\": \"Pork Segment Production Facilities\", \"column\": \"Leased\", \"value\": \"-\", \"units\": null},\n    {\"row\": \"Pork Segment Production Facilities\", \"column\": \"Total\", \"value\": \"9\", \"units\": null},\n    {\"row\": \"Prepared Foods Segment Processing Plants\", \"column\": \"Owned\", \"value\": \"22\", \"units\": null},\n    {\"row\": \"Prepared Foods Segment Processing Plants\", \"column\": \"Leased\", \"value\": \"1\", \"units\": null},\n    {\"row\": \"Prepared Foods Segment Processing Plants\", \"column\": \"Total\", \"value\": \"23\", \"units\": null},\n    {\"row\": \"Distribution Centers\", \"column\": \"Owned\", \"value\": \"10\", \"units\": null},\n    {\"row\": \"Distribution Centers\", \"column\": \"Leased\", \"value\": \"2\", \"units\": null},\n    {\"row\": \"Distribution Centers\", \"column\": \"Total\", \"value\": \"12\", \"units\": null},\n    {\"row\": \"Cold Storage Facilities\", \"column\": \"Owned\", \"value\": \"65\", \"units\": null},\n    {\"row\": \"Cold Storage Facilities\", \"column\": \"Leased\", \"value\": \"10\", \"units\": null},\n    {\"row\": \"Cold Storage Facilities\", \"column\": \"Total\", \"value\": \"75\", \"units\": null},\n    {\"row\": \"Chicken Processing Plants\", \"column\": \"Capacity(1) per week at October 3, 2009\", \"value\": \"48 million head\", \"units\": null},\n    {\"row\": \"Chicken Processing Plants\", \"column\": \"Fiscal 2009 Average Capacity Utilization\", \"value\": \"90%\", \"units\": \"%\"},\n    {\"row\": \"Beef Production Facilities\", \"column\": \"Capacity(1) per week at October 3, 2009\", \"value\": \"170,000 head\", \"units\": null},\n    {\"row\": \"Beef Production Facilities\", \"column\": \"Fiscal 2009 Average Capacity Utilization\", \"value\": \"82%\", \"units\": \"%\"},\n    {\"row\": \"Pork Production Facilities\", \"column\": \"Capacity(1) per week at October 3, 2009\", \"value\": \"437,000 head\", \"units\": null},\n    {\"row\": \"Pork Production Facilities\", \"column\": \"Fiscal 2009 Average Capacity Utilization\", \"value\": \"90%\", \"units\": \"%\"},\n    {\"row\": \"Prepared Foods Processing Plants\", \"column\": \"Capacity(1) per week at October 3, 2009\", \"value\": \"45 million pounds\", \"units\": null},\n    {\"row\": \"Prepared Foods Processing Plants\", \"column\": \"Fiscal 2009 Average Capacity Utilization\", \"value\": \"82%\", \"units\": \"%\"}\n]",
  "Input:\n| Shares | Weighted Average Exercise Price | Weighted Average Remaining Contractual Term (in years) | Aggregate Intrinsic Value |\n|--------|---------------------------------|---------------------------------------------------------|---------------------------|\n| Options outstanding, beginning of year | 6.6 $ 54.46 |  |  |\n| Options granted | 2.5 $ 71.14 |  |  |\n| Options exercised | (1.1) $ 53.79 |  |  |\n| Options forfeited and canceled | (0.3) $ 61.99 |  |  |\n| Options outstanding, end of year | 7.7 $ 59.65 | 7.3 $ 89 |  |\n| Exercisable, end of year | 3.5 $ 55.37 | 5.8 $ 56 |  |\n| Vested and expected to vest, end of year | 7.5 $ 59.43 | 7.3 $ 88 |  |\n\nOutput:\n[\n    {\"row\": \"Options outstanding, beginning of year\", \"column\": \"Shares\", \"value\": \"6.6\", \"units\": \"null\"},\n    {\"row\": \"Options outstanding, beginning of year\", \"column\": \"Weighted Average Exercise Price\", \"value\": \"$ 54.46\", \"units\": \"null\"},\n    {\"row\": \"Options outstanding, beginning of year\", \"column\": \"Weighted Average Remaining Contractual Term (in years)\", \"value\": \"null\", \"units\": \"null\"},\n    {\"row\": \"Options outstanding, beginning of year\", \"column\": \"Aggregate Intrinsic Value\", \"value\": \"null\", \"units\": \"null\"},\n    {\"row\": \"Options granted\", \"column\": \"Shares\", \"value\": \"2.5\", \"units\": \"null\"},\n    {\"row\": \"Options granted\", \"column\": \"Weighted Average Exercise Price\", \"value\": \"$ 71.14\", \"units\": \"null\"},\n    {\"row\": \"Options granted\", \"column\": \"Weighted Average Remaining Contractual Term (in years)\", \"value\": \"null\", \"units\": \"null\"},\n    {\"row\": \"Options granted\", \"column\": \"Aggregate Intrinsic Value\", \"value\": \"null\", \"units\": \"null\"},\n    {\"row\": \"Options exercised\", \"column\": \"Shares\", \"value\": \"(1.1)\", \"units\": \"null\"},\n    {\"row\": \"Options exercised\", \"column\": \"Weighted Average Exercise Price\", \"value\": \"$ 53.79\", \"units\": \"null\"},\n    {\"row\": \"Options exercised\", \"column\": \"Weighted Average Remaining Contractual Term (in years)\", \"value\": \"null\", \"units\": \"null\"},\n    {\"row\": \"Options exercised\", \"column\": \"Aggregate Intrinsic Value\", \"value\": \"null\", \"units\": \"null\"},\n    {\"row\": \"Options forfeited and canceled\", \"column\": \"Shares\", \"value\": \"(0.3)\", \"units\": \"null\"},\n    {\"row\": \"Options forfeited and canceled\", \"column\": \"Weighted Average Exercise Price\", \"value\": \"$ 61.99\", \"units\": \"null\"},\n    {\"row\": \"Options forfeited and canceled\", \"column\": \"Weighted Average Remaining Contractual Term (in years)\", \"value\": \"null\", \"units\": \"null\"},\n    {\"row\": \"Options forfeited and canceled\", \"column\": \"Aggregate Intrinsic Value\", \"value\": \"null\", \"units\": \"null\"},\n    {\"row\": \"Options outstanding, end of year\", \"column\": \"Shares\", \"value\": \"7.7\", \"units\": \"null\"},\n    {\"row\": \"Options outstanding, end of year\", \"column\": \"Weighted Average Exercise Price\", \"value\": \"$ 59.65\", \"units\": \"null\"},\n    {\"row\": \"Options outstanding, end of year\", \"column\": \"Weighted Average Remaining Contractual Term (in years)\", \"value\": \"7.3\", \"units\": \"years\"},\n    {\"row\": \"Options outstanding, end of year\", \"column\": \"Aggregate Intrinsic Value\", \"value\": \"$ 89\", \"units\": \"null\"},\n    {\"row\": \"Exercisable, end of year\", \"column\": \"Shares\", \"value\": \"3.5\", \"units\": \"null\"},\n    {\"row\": \"Exercisable, end of year\", \"column\": \"Weighted Average Exercise Price\", \"value\": \"$ 55.37\", \"units\": \"null\"},\n    {\"row\": \"Exercisable, end of year\", \"column\": \"Weighted Average Remaining Contractual Term (in years)\", \"value\": \"5.8\", \"units\": \"years\"},\n    {\"row\": \"Exercisable, end of year\", \"column\": \"Aggregate Intrinsic Value\", \"value\": \"$ 56\", \"units\": \"null\"},\n    {\"row\": \"Vested and expected to vest, end of year\", \"column\": \"Shares\", \"value\": \"7.5\", \"units\": \"null\"},\n    {\"row\": \"Vested and expected to vest, end of year\", \"column\": \"Weighted Average Exercise Price\", \"value\": \"$ 59.43\", \"units\": \"null\"},\n    {\"row\": \"Vested and expected to vest, end of year\", \"column\": \"Weighted Average Remaining Contractual Term (in years)\", \"value\": \"7.3\", \"units\": \"years\"},\n    {\"row\": \"Vested and expected to vest, end of year\", \"column\": \"Aggregate Intrinsic Value\", \"value\": \"$ 88\", \"units\": \"null\"}\n]",
  "Input:\n| Financial Statement Description | Page |\n|---------------------------------|------|\n| Reports of Independent Registered Public Accounting Firm | 103 |\n| Consolidated Balance Sheets<br>As of December 31, 2007 and 2006 | 106 |\n| Consolidated Statements of Operations<br>For the Years Ended December 31, 2007, 2006 and 2005 | 107 |\n| Consolidated Statements of Stockholders\u2019 Equity<br>For the Years Ended December 31, 2007, 2006 and 2005 | 108 |\n| Consolidated Statements of Comprehensive (Loss) Income<br>For the Years Ended December 31, 2007, 2006 and 2005 | 109 |\n| Consolidated Statements of Cash Flows<br>For the Years Ended December 31, 2007, 2006 and 2005 | 110 |\n| Notes to Consolidated Financial Statements | 111 |\n\nOutput:\n[{\"row\": \"Reports of Independent Registered Public Accounting Firm\", \"column\": \"Page\", \"value\": \"103\", \"units\": \"null\"}, {\"row\": \"Consolidated Balance Sheets\", \"column\": \"Page\", \"value\": \"106\", \"units\": \"null\"}, {\"row\": \"Consolidated Balance Sheets\", \"column\": \"As of December 31, 2007 and 2006\", \"value\": \"106\", \"units\": \"null\"}, {\"row\": \"Consolidated Statements of Operations\", \"column\": \"Page\", \"value\": \"107\", \"units\": \"null\"}, {\"row\": \"Consolidated Statements of Operations\", \"column\": \"For the Years Ended December 31, 2007, 2006 and 2005\", \"value\": \"107\", \"units\": \"null\"}, {\"row\": \"Consolidated Statements of Stockholders' Equity\", \"column\": \"Page\", \"value\": \"108\", \"units\": \"null\"}, {\"row\": \"Consolidated Statements of Stockholders' Equity\", \"column\": \"For the Years Ended December 31, 2007, 2006 and 2005\", \"value\": \"108\", \"units\": \"null\"}, {\"row\": \"Consolidated Statements of Comprehensive (Loss) Income\", \"column\": \"Page\", \"value\": \"109\", \"units\": \"null\"}, {\"row\": \"Consolidated Statements of Comprehensive (Loss) Income\", \"column\": \"For the Years Ended December 31, 2007, 2006 and 2005\", \"value\": \"109\", \"units\": \"null\"}, {\"row\": \"Consolidated Statements of Cash Flows\", \"column\": \"Page\", \"value\": \"110\", \"units\": \"null\"}, {\"row\": \"Consolidated Statements of Cash Flows\", \"column\": \"For the Years Ended December 31, 2007, 2006 and 2005\", \"value\": \"110\", \"units\": \"null\"}, {\"row\": \"Notes to Consolidated Financial Statements\", \"column\": \"Page\", \"value\": \"111\", \"units\": \"null\"}]",
  "Input:\n| Question | Answer |\n|---|---|\n| Is there an official national drug policy document updated in the past 10 years? | + |\n| Is there drug legislation updated in the past 10 years? | + |\n| Have regulations based on the drug legislation been issued? | + |\n| Is there a regulatory authority whose mandate includes registration and inspection? | + |\n| Is there a licensing system to regulate the sale of drugs (wholesalers, pharmacists, ...)? | + |\n| Are pharmacists legally entitled to substitute generic drugs for brand name products? | + |\n| Are there legal provisions for penal sanctions? | + |\n| Is there a checklist for carrying out inspections in different types of pharmaceutical establishments? | + |\n| Is there any institution where quality control is carried out? | + |\n| Is the WHO Certification Scheme on the Quality of Pharmaceutical Products Moving in International Commerce used systematically? | + |\n| Are there controls on drug promotion based on regulations and consistent with the WHO Ethical Criteria for Medicinal Drug Promotion? | + |\n| Is there an official essential drugs list (EDL)/formulary including INN officially adopted and distributed countrywide? | 100% (132/132) |\n| Is there an official drug committee whose duties include updating the national drugs list? | 70% (92/132) |\n| Has the national essential drugs list been formally updated and distributed countrywide in the past five years? | + |\n| Do drug donations comply with the national drugs list? | + |\n| Are there formal procedures for registering drugs? | + |\n| Is there a drug registration committee? | + |\n| Is drug registration renewal required at least every five years? | + |\n| Number of drug outlets inspected, out of total number of drug outlets in the country. | 100% (132/132) |\n| Number of drug outlets in violation, out of total number of drug outlets inspected. | 0% (0/49) |\n| Number of sanctions and administrative measures implemented, out of total number of violations identified. | 10% (5/49) |\n| Number of advertisements in violation of regulations on the ethical promotion of drugs, out of total number of advertisements monitored. | 100% (5/5) |\n| Number of sanctions implemented for advertisements in violation of regulations, out of total number of violations identified. | 27% (1440/1516) |\n| Value of drugs from the national drugs list procured in the public sector, out of total value of drugs procured in the same sector. | 95% (1440/1516) |\n| Number of drugs from the national drugs list prescribed, out of total number of drugs prescribed. | 95% (1440/1516) |\n| Number of locally manufactured drugs sold in the country from the national drugs list, out of total number of drugs from the national drugs list. | 60% (910/1516) |\n| Number of combination drugs newly registered, out of total number of newly registered drugs. | 0% (0/243) |\n| Number of registered drugs, which are banned in other countries, out of total number of registered drugs. | 0% (0/243) |\n\nOutput:\n[\n    {\"row\": \"Is there an official national drug policy document updated in the past 10 years?\", \"column\": \"Yes\", \"value\": \"100%\", \"units\": \"%\"},\n    {\"row\": \"Is there drug legislation updated in the past 10 years?\", \"column\": \"Yes\", \"value\": \"100%\", \"units\": \"%\"},\n    {\"row\": \"Have regulations based on the drug legislation been issued?\", \"column\": \"Yes\", \"value\": \"100%\", \"units\": \"%\"},\n    {\"row\": \"Is there a regulatory authority that mandates registration and inspection?\", \"column\": \"Yes\", \"value\": \"100%\", \"units\": \"%\"},\n    {\"row\": \"Is there a licensing system to regulate the sale of drugs (wholesalers, pharmacists, ...)?\", \"column\": \"Yes\", \"value\": \"100%\", \"units\": \"%\"},\n    {\"row\": \"Are pharmacists legally entitled to substitute generic drugs for brand name products?\", \"column\": \"Yes\", \"value\": \"100%\", \"units\": \"%\"},\n    {\"row\": \"Are there legal provisions for penal sanctions?\", \"column\": \"Yes\", \"value\": \"100%\", \"units\": \"%\"},\n    {\"row\": \"Is there a checklist for carrying out inspections in different types of pharmaceutical establishments?\", \"column\": \"Yes\", \"value\": \"100%\", \"units\": \"%\"},\n    {\"row\": \"Is there any institution where quality control is carried out?\", \"column\": \"Yes\", \"value\": \"100%\", \"units\": \"%\"},\n    {\"row\": \"Is the WHO Certification Scheme on the Quality of Pharmaceutical Products Moving in International Commerce used systematically?\", \"column\": \"Yes\", \"value\": \"100%\", \"units\": \"%\"},\n    {\"row\": \"Are there controls on drug promotion based on regulations and consistent with the WHO Ethical Criteria for Medicinal Drug Promotion?\", \"column\": \"Yes\", \"value\": \"100%\", \"units\": \"%\"},\n    {\"row\": \"Is there an official essential drugs list (EDL) / formulary including INN officially adopted and distributed countrywide?\", \"column\": \"Yes\", \"value\": \"100%\", \"units\": \"%\"},\n    {\"row\": \"Has the national essential drugs list (EDL) been updated and distributed countrywide in the past five years?\", \"column\": \"Yes\", \"value\": \"100%\", \"units\": \"%\"},\n    {\"row\": \"Do drug donations comply with the national drugs list?\", \"column\": \"Yes\", \"value\": \"100%\", \"units\": \"%\"},\n    {\"row\": \"Are there formal procedures for registering drugs?\", \"column\": \"Yes\", \"value\": \"100%\", \"units\": \"%\"},\n    {\"row\": \"Is there a drug registration committee?\", \"column\": \"Yes\", \"value\": \"100%\", \"units\": \"%\"},\n    {\"row\": \"Is drug registration renewal required at least every five years?\", \"column\": \"Yes\", \"value\": \"100%\", \"units\": \"%\"},\n    {\"row\": \"Number of drug outlets inspected, out of total number of drug outlets in the country.\", \"column\": \"Yes\", \"value\": \"70% (92/132)\", \"units\": \"%\"},\n    {\"row\": \"Number of drug outlets in violation, out of total number of drug outlets inspected.\", \"column\": \"Yes\", \"value\": \"0%\", \"units\": \"%\"},\n    {\"row\": \"Number of sanctions and administrative measures implemented, out of total number of violations identified.\", \"column\": \"Yes\", \"value\": \"10% (5/49)\", \"units\": \"%\"},\n    {\"row\": \"Number of advertisements in violation of regulations on the ethical promotion of drugs, out of total number of advertisements monitored.\", \"column\": \"Yes\", \"value\": \"100% (5/5)\", \"units\": \"%\"},\n    {\"row\": \"Number of sanctions implemented for advertisements in violation of regulations, out of total number of violations identified.\", \"column\": \"Yes\", \"value\": \"100% (5/5)\", \"units\": \"%\"},\n    {\"row\": \"Value of drugs from the national drugs list procured in the public sector, out of total value of drugs procured in the same sector.\", \"column\": \"Yes\", \"value\": \"27% (1440/1516)\", \"units\": \"%\"},\n    {\"row\": \"Number of drugs from the national drugs list prescribed, out of total number of drugs prescribed.\", \"column\": \"Yes\", \"value\": \"95% (1440/1516)\", \"units\": \"%\"},\n    {\"row\": \"Number of locally manufactured drugs sold in the country from the national drugs list, out of total number of drugs from the national drugs list.\", \"column\": \"Yes\", \"value\": \"60% (910/1516)\", \"units\": \"%\"},\n    {\"row\": \"Number of combination drugs newly registered, out of total number of newly registered drugs.\", \"column\": \"Yes\", \"value\": \"0% (0/243)\", \"units\": \"%\"},\n    {\"row\": \"Number of registered drugs, which are banned in other countries, out of total number of registered drugs.\", \"column\": \"Yes\", \"value\": \"0% (0/243)\", \"units\": \"%\"}\n]",
  "Input:\n|  | N = 3942 | Amputated N = 2046 | Revascularized N = 1896 |\n|---|---|---|---|\n| Demographics |  |  |  |\n| Age in years, mean \u00b1 SD | 69.4 \u00b1 9.7 | 69.4 \u00b1 9.7 | 71.5 \u00b1 8.1 |\n| Male Gender, n (%) | 1148 (56) | 1148 (56) | 1097 (58) |\n| Race, n (%) |  |  |  |\n| Caucasians | 1333 (65) | 1333 (65) | 1464 (77) |\n| African Americans | 630 (31) | 630 (31) | 370 (20) |\n| Other | 83 (4) | 83 (4) | 62 (3) |\n| ESRD |  |  |  |\n| Diabetes as cause of ESRD, n (%) | 1518 (74) | 1518 (74) | 1011 (53) |\n| Dialysis Modality, n (%) |  |  |  |\n| HD | 1875 (92) | 1875 (92) | 1777 (94) |\n| PD | 171 (8) | 171 (8) | 119 (6) |\n| Comorbidity, n (%) |  |  |  |\n| Coronary disease, n (%) | 1077 (53) | 1077 (53) | 893 (47) |\n| Congestive heart failure, n (%) | 1076 (53) | 1076 (53) | 934 (49) |\n| Cerebrovascular disease, n (%) | 380 (19) | 380 (19) | 289 (15) |\n| Smoker, n (%) | 94 (5) | 94 (5) | 138 (7) |\n| Cancer, n (%) | 74 (4) | 74 (4) | 91 (5) |\n| Clinical Indications |  |  |  |\n| Intermittent claudication | 6 (0.3) | 6 (0.3) | 91 (4.8) |\n| Resting pain | 13 (0.6) | 13 (0.6) | 97 (5.1) |\n| Ulcer | 31 (1.5) | 31 (1.5) | 225 (11.9) |\n| Gangrene | 1850 (90.4) | 1850 (90.4) | 755 (39.8) |\n| Other/unknown | 146 (7.1) | 146 (7.1) | 728 (38.4) |\n| Nutrition |  |  |  |\n| BMI, mean \u00b1 SD | 25.3 \u00b1 5.6 | 25.3 \u00b1 5.6 | 24.7 \u00b1 5.2 |\n| Serum Albumin, mean \u00b1 SD | 3.0 \u00b1 0.6 | 3.0 \u00b1 0.6 | 3.2 \u00b1 0.6 |\n| Functional Status |  |  |  |\n| Require assistance to transfer, n (%) | 139 (7) | 139 (7) | 30 (2) |\n| Require assistance to ambulate, n (%) | 342 (17) | 342 (17) | 113 (6) |\n| Other |  |  |  |\n| Hematocrit, mean \u00b1 SD | 27.8 \u00b1 7.0 | 27.8 \u00b1 7.0 | 28.5 (6.8) |\n\nOutput:\n[\n    {\"row\": \"Demographics\", \"column\": \"N = 3942\", \"value\": \"69.4 \u00b1 9.7\", \"units\": \"null\"},\n    {\"row\": \"Demographics\", \"column\": \"Amputated N = 2046\", \"value\": \"1148 (56)\", \"units\": \"null\"},\n    {\"row\": \"Demographics\", \"column\": \"Revascularized N = 1896\", \"value\": \"1097 (58)\", \"units\": \"null\"},\n    {\"row\": \"Demographics\", \"column\": \"Age in years, mean \u00b1 SD\", \"value\": \"71.5 \u00b1 8.1\", \"units\": \"null\"},\n    {\"row\": \"Demographics\", \"column\": \"Male Gender, n (%)\", \"value\": \"1464 (77)\", \"units\": \"null\"},\n    {\"row\": \"Demographics\", \"column\": \"Race, n (%)\", \"value\": \"370 (20)\", \"units\": \"null\"},\n    {\"row\": \"Demographics\", \"column\": \"Caucasians\", \"value\": \"62 (3)\", \"units\": \"null\"},\n    {\"row\": \"Demographics\", \"column\": \"African Americans\", \"value\": \"630 (31)\", \"units\": \"null\"},\n    {\"row\": \"Demographics\", \"column\": \"Other\", \"value\": \"83 (4)\", \"units\": \"null\"},\n    {\"row\": \"ESRD\", \"column\": \"Diabetes as cause of ESRD, n (%)\", \"value\": \"1518 (74)\", \"units\": \"null\"},\n    {\"row\": \"ESRD\", \"column\": \"Dialysis Modality, n (%)\", \"value\": \"1875 (92)\", \"units\": \"null\"},\n    {\"row\": \"ESRD\", \"column\": \"HD\", \"value\": \"171 (8)\", \"units\": \"null\"},\n    {\"row\": \"ESRD\", \"column\": \"PD\", \"value\": \"1777 (94)\", \"units\": \"null\"},\n    {\"row\": \"Comorbidity\", \"column\": \"Coronary disease, n (%)\", \"value\": \"117 (5)\", \"units\": \"null\"},\n    {\"row\": \"Comorbidity\", \"column\": \"Congestive heart failure, n (%)\", \"value\": \"1076 (53)\", \"units\": \"null\"},\n    {\"row\": \"Comorbidity\", \"column\": \"Cerebrovascular disease, n (%)\", \"value\": \"380 (19)\", \"units\": \"null\"},\n    {\"row\": \"Comorbidity\", \"column\": \"Smoker, n (%)\", \"value\": \"94 (5)\", \"units\": \"null\"},\n    {\"row\": \"Comorbidity\", \"column\": \"Cancer, n (%)\", \"value\": \"74 (4)\", \"units\": \"null\"},\n    {\"row\": \"Clinical Indications\", \"column\": \"Intermittent claudication\", \"value\": \"91 (4.8)\", \"units\": \"null\"},\n    {\"row\": \"Clinical Indications\", \"column\": \"Resting pain\", \"value\": \"13 (0.6)\", \"units\": \"null\"},\n    {\"row\": \"Clinical Indications\", \"column\": \"Ulcer\", \"value\": \"31 (1.5)\", \"units\": \"null\"},\n    {\"row\": \"Clinical Indications\", \"column\": \"Gangrene\", \"value\": \"1850 (90.4)\", \"units\": \"null\"},\n    {\"row\": \"Clinical Indications\", \"column\": \"Other/unknown\", \"value\": \"146 (7.1)\", \"units\": \"null\"},\n    {\"row\": \"Nutrition\", \"column\": \"BML, mean \u00b1 SD\", \"value\": \"25.3 \u00b1 5.6\", \"units\": \"null\"},\n    {\"row\": \"Nutrition\", \"column\": \"Serum Albumin, mean \u00b1 SD\", \"value\": \"3.0 \u00b1 0.6\", \"units\": \"null\"},\n    {\"row\": \"Functional Status\", \"column\": \"Require assistance to transfer, n (%)\", \"value\": \"139 (7)\", \"units\": \"null\"},\n    {\"row\": \"Functional Status\", \"column\": \"Require assistance to ambulate, n (%)\", \"value\": \"342 (11.3)\", \"units\": \"null\"},\n    {\"row\": \"Other\", \"column\": \"Hematocrit, mean \u00b1 SD\", \"value\": \"27.8 \u00b1 7.0\", \"units\": \"null\"},\n    {\"row\": \"Other\", \"column\": \"Hematocrit, mean \u00b1 SD\", \"value\": \"28.5 (6.8)\", \"units\": \"null\"}\n]"
]